README.md
setup.py
unionService/APICall.py
unionService/Dingdanxia.py
unionService/JDUnion.py
unionService/__init__.py
unionService.egg-info/PKG-INFO
unionService.egg-info/SOURCES.txt
unionService.egg-info/dependency_links.txt
unionService.egg-info/requires.txt
unionService.egg-info/top_level.txt