Metadata-Version: 1.0
Name: unionService
Version: 0.1.3
Summary: alibaba taobao & jd union service
Home-page: https://github.com/harrett/unionService.git
Author: harrett
Author-email: harrett@163.com
License: MIT Licence
Keywords: union,taobao,jd,jingdong
Platform: any
